codevec/__init__.py
codevec/cli.py
codevec/index.py
codevec/models.py
codevec/search.py
codevec/server.py
codevec-1.0.0.dist-info/licenses/LICENSE
codevec-1.0.0.dist-info/METADATA
codevec-1.0.0.dist-info/WHEEL
codevec-1.0.0.dist-info/entry_points.txt
codevec-1.0.0.dist-info/top_level.txt
codevec-1.0.0.dist-info/RECORD
