Metadata-Version: 2.4
Name: codevec
Version: 1.0.0
Summary: Semantic search for functions in Python codebases
Author-email: Lucas Monroe <lucas.i.monroe1@gmail.com>
License-Expression: Apache-2.0
Project-URL: Homepage, https://github.com/mlucas55/codevec
Project-URL: Bug Tracker, https://github.com/mlucas55/codevec/issues
Project-URL: Source, https://github.com/mlucas55/codevec
Keywords: semantic search,code search,embeddings,vector search,python
Classifier: Development Status :: 4 - Beta
Classifier: Intended Audience :: Developers
Classifier: Operating System :: OS Independent
Classifier: Programming Language :: Python :: 3
Classifier: Programming Language :: Python :: 3.10
Classifier: Programming Language :: Python :: 3.11
Classifier: Programming Language :: Python :: 3.12
Classifier: Programming Language :: Python :: 3.13
Classifier: Topic :: Software Development :: Libraries :: Python Modules
Classifier: Topic :: Text Processing :: Indexing
Requires-Python: >=3.10
License-File: LICENSE
Requires-Dist: chromadb<2.0.0,>=1.3.7
Requires-Dist: sentence-transformers==5.2.0
Requires-Dist: fastapi>=0.100.0
Requires-Dist: uvicorn>=0.23.0
Requires-Dist: requests>=2.28.0
Dynamic: license-file
